panqt-0.2.2-py3.5-nspkg.pth
panqt/compat.py
panqt/encoding.py
panqt/excepthook.py
panqt/utils.py
panqt/_lib/magic/libgcc_s_dw2-1.dll
panqt/_lib/magic/libmagic-1.dll
panqt/_lib/magic/libregex-1.dll
panqt/_lib/magic/magic1.dll
panqt/_lib/magic/zlib1.dll
panqt/_lib/magic/db/magic.mgc
panqt/i18n/de.qm
panqt/models/ColumnDtypeModel.py
panqt/models/DataFrameModel.py
panqt/models/DataSearch.py
panqt/models/ProgressThread.py
panqt/models/SupportedDtypes.py
panqt/models/__init__.py
panqt/models/mime.py
panqt/ui/__init__.py
panqt/ui/fallback/__init__.py
panqt/ui/fallback/easygui/__init__.py
panqt/ui/fallback/easygui/easygui.py
panqt/ui/fallback/easygui/boxes/__init__.py
panqt/ui/fallback/easygui/boxes/about.py
panqt/ui/fallback/easygui/boxes/base_boxes.py
panqt/ui/fallback/easygui/boxes/derived_boxes.py
panqt/ui/fallback/easygui/boxes/egstore.py
panqt/ui/fallback/easygui/boxes/state.py
panqt/ui/fallback/easygui/boxes/text_box.py
panqt/ui/fallback/easygui/boxes/updatable_text_box.py
panqt/ui/fallback/easygui/boxes/utils.py
panqt/views/BigIntSpinbox.py
panqt/views/CSVDialogs.py
panqt/views/CustomDelegates.py
panqt/views/DataTableView.py
panqt/views/EditDialogs.py
panqt/views/MultiFileDialogs.py
panqt/views/OverlayProgressView.py
panqt/views/__init__.py
panqt/views/_ui/__init__.py
panqt/views/_ui/icons_rc.py
panqt-0.2.2.dist-info/DESCRIPTION.rst
panqt-0.2.2.dist-info/METADATA
panqt-0.2.2.dist-info/RECORD
panqt-0.2.2.dist-info/WHEEL
panqt-0.2.2.dist-info/metadata.json
panqt-0.2.2.dist-info/namespace_packages.txt
panqt-0.2.2.dist-info/top_level.txt
