Metadata-Version: 2.0
Name: panqt
Version: 0.2.2
Summary: Utilities to use pandas (the data analysis / manipulation library for Python) with Qt.
Home-page: https://github.com/datalyze-solutions/panqt
Author: Matthias Ludwig, Marcel Radischat
Author-email: m.Ludwig@datalyze-solutions.com
License: MIT License
Platform: any
Classifier: Programming Language :: Python
Classifier: Development Status :: 4 - Beta
Classifier: Natural Language :: German
Classifier: Environment :: X11 Applications :: Qt
Classifier: Intended Audience :: Developers
Classifier: License :: OSI Approved :: BSD License
Classifier: Operating System :: OS Independent
Classifier: Topic :: Software Development :: Libraries :: Python Modules
Classifier: Topic :: Software Development :: User Interfaces
Requires-Dist: easygui
Requires-Dist: pandas (==0.17.1)
Requires-Dist: pytest
Requires-Dist: pytest-cov
Requires-Dist: pytest-qt (==1.2.2)
Requires-Dist: python-magic (==0.4.6)
Provides-Extra: testing
Requires-Dist: easygui; extra == 'testing'
Requires-Dist: pandas (==0.17.1); extra == 'testing'
Requires-Dist: pyside; extra == 'testing'
Requires-Dist: pytest; extra == 'testing'
Requires-Dist: pytest-cov; extra == 'testing'
Requires-Dist: pytest-qt; extra == 'testing'
Requires-Dist: python-magic (==0.4.6); extra == 'testing'
